{
    "scitex_schema": "scitex.plt.figure.editable",
    "scitex_schema_version": "0.3.0",
    "meta": {
        "title": "",
        "description": "",
        "exported_at": "2026-05-07T08:02:42.385532"
    },
    "figure": {
        "size_px": [
            2998,
            2394
        ],
        "dpi": 300,
        "figsize_inches": [
            10.0,
            8.0
        ]
    },
    "axes": {
        "ax_00": {
            "bbox_px": {
                "x0": 375,
                "y0": 288,
                "x1": 2700,
                "y1": 831
            },
            "position": [
                0.125,
                0.6535294117647059,
                0.775,
                0.2264705882352941
            ],
            "xlim": [
                -0.04990234375,
                1.04794921875
            ],
            "ylim": [
                -1.0980987966060638,
                1.0999094665050506
            ]
        },
        "ax_01": {
            "bbox_px": {
                "x0": 375,
                "y0": 940,
                "x1": 2700,
                "y1": 1483
            },
            "position": [
                0.125,
                0.3817647058823529,
                0.775,
                0.2264705882352941
            ],
            "xlim": [
                -0.04990234375,
                1.04794921875
            ],
            "ylim": [
                0.09059061259031295,
                1.0434106126427651
            ]
        },
        "ax_02": {
            "bbox_px": {
                "x0": 375,
                "y0": 1592,
                "x1": 2700,
                "y1": 2136
            },
            "position": [
                0.125,
                0.10999999999999999,
                0.775,
                0.2264705882352941
            ],
            "xlim": [
                -0.04990234375,
                1.04794921875
            ],
            "ylim": [
                -3.4544249773025513,
                3.446677803993225
            ]
        }
    },
    "elements": {
        "ax_00_line_00": {
            "id": "ax_00_line_00",
            "axes_id": "ax_00",
            "element_type": "line",
            "label": "signal",
            "geometry_px": {
                "coord_space": "axes",
                "bbox": {
                    "x0": 106,
                    "y0": 25,
                    "x1": 2219,
                    "y1": 518
                },
                "path_simplified": [
                    [
                        105.7,
                        238.3
                    ],
                    [
                        114.0,
                        238.3
                    ],
                    [
                        122.2,
                        240.4
                    ],
                    [
                        134.6,
                        247.9
                    ],
                    [
                        142.9,
                        255.5
                    ],
                    [
                        151.2,
                        264.7
                    ],
                    [
                        176.0,
                        296.8
                    ],
                    [
                        188.4,
                        310.4
                    ],
                    [
                        192.5,
                        313.8
                    ],
                    [
                        200.8,
                        318.5
                    ],
                    [
                        209.1,
                        319.6
                    ],
                    [
                        217.4,
                        317.0
                    ],
                    [
                        221.5,
                        314.1
                    ],
                    [
                        229.8,
                        305.5
                    ],
                    [
                        233.9,
                        299.8
                    ],
                    [
                        242.2,
                        286.2
                    ],
                    [
                        271.1,
                        230.2
                    ],
                    [
                        279.4,
                        218.0
                    ],
                    [
                        283.5,
                        213.4
                    ],
                    [
                        287.7,
                        210.1
                    ],
                    [
                        291.8,
                        208.3
                    ],
                    [
                        296.0,
                        207.9
                    ],
                    [
                        300.1,
                        209.1
                    ],
                    [
                        304.2,
                        211.9
                    ],
                    [
                        308.4,
                        216.3
                    ],
                    [
                        312.5,
                        222.3
                    ],
                    [
                        320.8,
                        238.4
                    ],
                    [
                        329.0,
                        259.1
                    ],
                    [
                        349.7,
                        316.7
                    ],
                    [
                        358.0,
                        335.6
                    ],
                    [
                        362.1,
                        342.8
                    ],
                    [
                        366.3,
                        348.2
                    ],
                    [
                        370.4,
                        351.5
                    ],
                    [
                        374.5,
                        352.7
                    ],
                    [
                        378.7,
                        351.5
                    ],
                    [
                        382.8,
                        347.8
                    ],
                    [
                        386.9,
                        341.9
                    ],
                    [
                        391.1,
                        333.6
                    ],
                    [
                        399.4,
                        311.1
                    ],
                    [
                        403.5,
                        297.4
                    ],
                    [
                        424.2,
                        220.4
                    ],
                    [
                        432.4,
                        194.9
                    ],
                    [
                        436.6,
                        185.2
                    ],
                    [
                        440.7,
                        178.1
                    ],
                    [
                        444.9,
                        174.0
                    ],
                    [
                        449.0,
                        173.1
                    ],
                    [
                        453.1,
                        175.4
                    ],
                    [
                        457.3,
                        181.1
                    ],
                    [
                        461.4,
                        190.1
                    ],
                    [
                        469.7,
                        216.8
                    ],
                    [
                        494.5,
                        332.1
                    ],
                    [
                        502.8,
                        364.2
                    ],
                    [
                        506.9,
                        375.9
                    ],
                    [
                        511.0,
                        384.0
                    ],
                    [
                        515.2,
                        388.1
                    ],
                    [
                        519.3,
                        387.8
                    ],
                    [
                        523.4,
                        383.0
                    ],
                    [
                        527.6,
                        373.9
                    ],
                    [
                        535.9,
                        343.4
                    ],
                    [
                        544.1,
                        300.2
                    ],
                    [
                        560.7,
                        202.1
                    ],
                    [
                        568.9,
                        163.1
                    ],
                    [
                        573.1,
                        149.4
                    ],
                    [
                        577.2,
                        140.5
                    ],
                    [
                        581.4,
                        137.1
                    ],
                    [
                        585.5,
                        139.3
                    ],
                    [
                        589.6,
                        147.2
                    ],
                    [
                        593.8,
                        160.7
                    ],
                    [
                        597.9,
                        179.3
                    ],
                    [
                        606.2,
                        228.8
                    ],
                    [
                        626.9,
                        372.3
                    ],
                    [
                        631.0,
                        393.8
                    ],
                    [
                        635.1,
                        410.2
                    ],
                    [
                        639.3,
                        420.4
                    ],
                    [
                        643.4,
                        423.8
                    ],
                    [
                        647.5,
                        420.1
                    ],
                    [
                        651.7,
                        409.3
                    ],
                    [
                        655.8,
                        391.8
                    ],
                    [
                        664.1,
                        339.4
                    ],
                    [
                        680.6,
                        202.1
                    ],
                    [
                        688.9,
                        143.6
                    ],
                    [
                        693.0,
                        122.6
                    ],
                    [
                        697.2,
                        108.9
                    ],
                    [
                        701.3,
                        103.3
                    ],
                    [
                        705.4,
                        106.2
                    ],
                    [
                        709.6,
                        117.8
                    ],
                    [
                        713.7,
                        137.6
                    ],
                    [
                        722.0,
                        198.1
                    ],
                    [
                        738.5,
                        355.6
                    ],
                    [
                        746.8,
                        419.5
                    ],
                    [
                        750.9,
                        440.7
                    ],
                    [
                        755.1,
                        453.0
                    ],
                    [
                        759.2,
                        455.3
                    ],
                    [
                        763.3,
                        447.3
                    ],
                    [
                        767.5,
                        429.3
                    ],
                    [
                        771.6,
                        402.0
                    ],
                    [
                        779.9,
                        325.9
                    ],
                    [
                        792.3,
                        190.7
                    ],
                    [
                        800.6,
                        116.7
                    ],
                    [
                        804.7,
                        91.7
                    ],
                    [
                        808.8,
                        77.2
                    ],
                    [
                        813.0,
                        74.2
                    ],
                    [
                        817.1,
                        83.2
                    ],
                    [
                        821.3,
                        103.7
                    ],
                    [
                        825.4,
                        134.8
                    ],
                    [
                        833.7,
                        221.1
                    ],
                    [
                        850.2,
                        413.1
                    ],
                    [
                        854.3,
                        447.2
                    ],
                    [
                        858.5,
                        470.5
                    ],
                    [
                        862.6,
                        481.3
                    ],
                    [
                        866.8,
                        478.6
                    ],
                    [
                        870.9,
                        462.4
                    ],
                    [
                        875.0,
                        433.6
                    ],
                    [
                        883.3,
                        345.3
                    ],
                    [
                        899.8,
                        133.4
                    ],
                    [
                        904.0,
                        93.9
                    ],
                    [
                        908.1,
                        66.2
                    ],
                    [
                        912.3,
                        52.3
                    ],
                    [
                        916.4,
                        53.4
                    ],
                    [
                        920.5,
                        69.7
                    ],
                    [
                        924.7,
                        100.4
                    ],
                    [
                        928.8,
                        143.3
                    ],
                    [
                        945.3,
                        371.9
                    ],
                    [
                        953.6,
                        463.3
                    ],
                    [
                        957.8,
                        490.1
                    ],
                    [
                        961.9,
                        501.2
                    ],
                    [
                        966.0,
                        495.4
                    ],
                    [
                        970.2,
                        473.1
                    ],
                    [
                        974.3,
                        435.5
                    ],
                    [
                        982.6,
                        326.3
                    ],
                    [
                        995.0,
                        140.7
                    ],
                    [
                        999.1,
                        91.9
                    ],
                    [
                        1003.3,
                        56.6
                    ],
                    [
                        1007.4,
                        37.8
                    ],
                    [
                        1011.5,
                        37.0
                    ],
                    [
                        1015.7,
                        54.6
                    ],
                    [
                        1019.8,
                        89.4
                    ],
                    [
                        1023.9,
                        138.9
                    ],
                    [
                        1036.3,
                        333.3
                    ],
                    [
                        1044.6,
                        449.4
                    ],
                    [
                        1048.8,
                        488.4
                    ],
                    [
                        1052.9,
                        510.0
                    ],
                    [
                        1057.0,
                        512.0
                    ],
                    [
                        1061.2,
                        494.1
                    ],
                    [
                        1065.3,
                        457.7
                    ],
                    [
                        1069.4,
                        405.5
                    ],
                    [
                        1081.8,
                        201.7
                    ],
                    [
                        1090.1,
                        83.6
                    ],
                    [
                        1094.3,
                        46.1
                    ],
                    [
                        1098.4,
                        27.9
                    ],
                    [
                        1102.5,
                        30.8
                    ],
                    [
                        1106.7,
                        54.8
                    ],
                    [
                        1110.8,
                        97.8
                    ],
                    [
                        1131.5,
                        432.5
                    ],
                    [
                        1135.6,
                        480.8
                    ],
                    [
                        1139.8,
                        510.4
                    ],
                    [
                        1143.9,
                        518.3
                    ],
                    [
                        1148.0,
                        503.7
                    ],
                    [
                        1152.2,
                        467.8
                    ],
                    [
                        1156.3,
                        413.7
                    ],
                    [
                        1172.8,
                        129.2
                    ],
                    [
                        1177.0,
                        74.7
                    ],
                    [
                        1181.1,
                        38.8
                    ],
                    [
                        1185.2,
                        25.0
                    ],
                    [
                        1189.4,
                        34.8
                    ],
                    [
                        1193.5,
                        67.4
                    ],
                    [
                        1197.7,
                        119.7
                    ],
                    [
                        1214.2,
                        408.9
                    ],
                    [
                        1218.3,
                        465.4
                    ],
                    [
                        1222.5,
                        502.7
                    ],
                    [
                        1226.6,
                        517.0
                    ],
                    [
                        1230.7,
                        506.7
                    ],
                    [
                        1234.9,
                        472.8
                    ],
                    [
                        1239.0,
                        418.7
                    ],
                    [
                        1251.4,
                        195.5
                    ],
                    [
                        1259.7,
                        72.1
                    ],
                    [
                        1263.8,
                        38.7
                    ],
                    [
                        1268.0,
                        29.5
                    ],
                    [
                        1272.1,
                        45.7
                    ],
                    [
                        1276.2,
                        85.6
                    ],
                    [
                        1280.4,
                        145.1
                    ],
                    [
                        1296.9,
                        436.8
                    ],
                    [
                        1301.1,
                        483.7
                    ],
                    [
                        1305.2,
                        507.6
                    ],
                    [
                        1309.3,
                        505.7
                    ],
                    [
                        1313.5,
                        478.4
                    ],
                    [
                        1317.6,
                        428.4
                    ],
                    [
                        1330.0,
                        206.5
                    ],
                    [
                        1338.3,
                        80.9
                    ],
                    [
                        1342.4,
                        47.3
                    ],
                    [
                        1346.6,
                        39.2
                    ],
                    [
                        1350.7,
                        57.5
                    ],
                    [
                        1354.8,
                        100.1
                    ],
                    [
                        1359.0,
                        162.2
                    ],
                    [
                        1371.4,
                        387.6
                    ],
                    [
                        1375.5,
                        446.7
                    ],
                    [
                        1379.7,
                        485.2
                    ],
                    [
                        1383.8,
                        498.5
                    ],
                    [
                        1387.9,
                        485.0
                    ],
                    [
                        1392.1,
                        446.5
                    ],
                    [
                        1396.2,
                        387.4
                    ],
                    [
                        1408.6,
                        164.7
                    ],
                    [
                        1412.7,
                        105.1
                    ],
                    [
                        1416.9,
                        66.0
                    ],
                    [
                        1421.0,
                        52.1
                    ],
                    [
                        1425.2,
                        65.0
                    ],
                    [
                        1429.3,
                        103.2
                    ],
                    [
                        1433.4,
                        161.9
                    ],
                    [
                        1445.8,
                        380.8
                    ],
                    [
                        1450.0,
                        437.7
                    ],
                    [
                        1454.1,
                        473.3
                    ],
                    [
                        1458.2,
                        483.4
                    ],
                    [
                        1462.4,
                        466.7
                    ],
                    [
                        1466.5,
                        425.3
                    ],
                    [
                        1470.7,
                        364.7
                    ],
                    [
                        1483.1,
                        151.6
                    ],
                    [
                        1487.2,
                        100.8
                    ],
                    [
                        1491.3,
                        72.6
                    ],
                    [
                        1495.5,
                        70.5
                    ],
                    [
                        1499.6,
                        94.8
                    ],
                    [
                        1503.7,
                        142.2
                    ],
                    [
                        1520.3,
                        408.8
                    ],
                    [
                        1524.4,
                        449.7
                    ],
                    [
                        1528.6,
                        466.4
                    ],
                    [
                        1532.7,
                        456.6
                    ],
                    [
                        1536.8,
                        421.9
                    ],
                    [
                        1541.0,
                        367.1
                    ],
                    [
                        1553.4,
                        165.3
                    ],
                    [
                        1557.5,
                        116.5
                    ],
                    [
                        1561.7,
                        89.8
                    ],
                    [
                        1565.8,
                        88.6
                    ],
                    [
                        1569.9,
                        112.9
                    ],
                    [
                        1574.1,
                        159.3
                    ],
                    [
                        1586.5,
                        354.2
                    ],
                    [
                        1590.6,
                        406.8
                    ],
                    [
                        1594.7,
                        439.6
                    ],
                    [
                        1598.9,
                        448.0
                    ],
                    [
                        1603.0,
                        431.0
                    ],
                    [
                        1607.1,
                        391.2
                    ],
                    [
                        1623.7,
                        151.8
                    ],
                    [
                        1627.8,
                        116.5
                    ],
                    [
                        1632.0,
                        104.4
                    ],
                    [
                        1636.1,
                        117.2
                    ],
                    [
                        1640.2,
                        152.9
                    ],
                    [
                        1656.8,
                        382.1
                    ],
                    [
                        1660.9,
                        417.2
                    ],
                    [
                        1665.1,
                        429.7
                    ],
                    [
                        1669.2,
                        418.0
                    ],
                    [
                        1673.3,
                        384.2
                    ],
                    [
                        1689.9,
                        165.6
                    ],
                    [
                        1694.0,
                        133.3
                    ],
                    [
                        1698.1,
                        123.1
                    ],
                    [
                        1702.3,
                        136.2
                    ],
                    [
                        1706.4,
                        170.5
                    ],
                    [
                        1718.8,
                        332.9
                    ],
                    [
                        1723.0,
                        377.8
                    ],
                    [
                        1727.1,
                        405.1
                    ],
                    [
                        1731.2,
                        410.5
                    ],
                    [
                        1735.4,
                        393.6
                    ],
                    [
                        1739.5,
                        357.3
                    ],
                    [
                        1751.9,
                        202.0
                    ],
                    [
                        1756.1,
                        163.4
                    ],
                    [
                        1760.2,
                        143.2
                    ],
                    [
                        1764.3,
                        144.5
                    ],
                    [
                        1768.5,
                        166.8
                    ],
                    [
                        1772.6,
                        206.1
                    ],
                    [
                        1785.0,
                        352.0
                    ],
                    [
                        1789.1,
                        382.4
                    ],
                    [
                        1793.3,
                        393.7
                    ],
                    [
                        1797.4,
                        384.1
                    ],
                    [
                        1801.6,
                        355.6
                    ],
                    [
                        1814.0,
                        217.9
                    ],
                    [
                        1818.1,
                        181.4
                    ],
                    [
                        1822.2,
                        161.1
                    ],
                    [
                        1826.4,
                        160.3
                    ],
                    [
                        1830.5,
                        178.9
                    ],
                    [
                        1834.6,
                        213.4
                    ],
                    [
                        1847.1,
                        342.6
                    ],
                    [
                        1851.2,
                        368.8
                    ],
                    [
                        1855.3,
                        377.2
                    ],
                    [
                        1859.5,
                        366.7
                    ],
                    [
                        1863.6,
                        339.5
                    ],
                    [
                        1876.0,
                        217.4
                    ],
                    [
                        1880.1,
                        188.1
                    ],
                    [
                        1884.3,
                        174.6
                    ],
                    [
                        1888.4,
                        179.0
                    ],
                    [
                        1892.6,
                        200.2
                    ],
                    [
                        1905.0,
                        313.2
                    ],
                    [
                        1909.1,
                        343.6
                    ],
                    [
                        1913.2,
                        360.1
                    ],
                    [
                        1917.4,
                        359.8
                    ],
                    [
                        1921.5,
                        343.1
                    ],
                    [
                        1938.1,
                        209.1
                    ],
                    [
                        1942.2,
                        191.5
                    ],
                    [
                        1946.3,
                        189.5
                    ],
                    [
                        1950.5,
                        203.3
                    ],
                    [
                        1954.6,
                        229.8
                    ],
                    [
                        1967.0,
                        327.5
                    ],
                    [
                        1971.1,
                        344.9
                    ],
                    [
                        1975.3,
                        347.7
                    ],
                    [
                        1979.4,
                        335.6
                    ],
                    [
                        1983.6,
                        311.2
                    ],
                    [
                        1991.8,
                        247.3
                    ],
                    [
                        1996.0,
                        220.4
                    ],
                    [
                        2000.1,
                        204.4
                    ],
                    [
                        2004.2,
                        202.0
                    ],
                    [
                        2008.4,
                        213.7
                    ],
                    [
                        2012.5,
                        236.6
                    ],
                    [
                        2024.9,
                        320.3
                    ],
                    [
                        2029.0,
                        334.2
                    ],
                    [
                        2033.2,
                        335.1
                    ],
                    [
                        2037.3,
                        323.0
                    ],
                    [
                        2041.5,
                        300.8
                    ],
                    [
                        2049.7,
                        245.8
                    ],
                    [
                        2053.9,
                        224.6
                    ],
                    [
                        2058.0,
                        213.5
                    ],
                    [
                        2062.1,
                        214.9
                    ],
                    [
                        2066.3,
                        228.0
                    ],
                    [
                        2078.7,
                        300.3
                    ],
                    [
                        2082.8,
                        318.1
                    ],
                    [
                        2087.0,
                        325.6
                    ],
                    [
                        2091.1,
                        321.6
                    ],
                    [
                        2095.2,
                        307.0
                    ],
                    [
                        2107.6,
                        240.1
                    ],
                    [
                        2111.8,
                        226.3
                    ],
                    [
                        2115.9,
                        222.6
                    ],
                    [
                        2120.0,
                        229.6
                    ],
                    [
                        2124.2,
                        245.6
                    ],
                    [
                        2136.6,
                        306.0
                    ],
                    [
                        2140.7,
                        315.5
                    ],
                    [
                        2144.9,
                        315.1
                    ],
                    [
                        2149.0,
                        305.1
                    ],
                    [
                        2161.4,
                        249.0
                    ],
                    [
                        2165.5,
                        235.8
                    ],
                    [
                        2169.7,
                        231.0
                    ],
                    [
                        2173.8,
                        235.5
                    ],
                    [
                        2178.0,
                        248.0
                    ],
                    [
                        2190.4,
                        299.1
                    ],
                    [
                        2194.5,
                        307.5
                    ],
                    [
                        2198.6,
                        307.6
                    ],
                    [
                        2202.8,
                        299.4
                    ],
                    [
                        2215.2,
                        252.5
                    ],
                    [
                        2219.3,
                        241.8
                    ]
                ],
                "path": null
            },
            "style": {
                "color": [
                    0,
                    0,
                    0
                ],
                "linewidth": 0.3401574803149607,
                "linestyle": "-",
                "alpha": null,
                "marker": "None",
                "markersize": 2.267716535433071
            },
            "editable_styles": [
                "color",
                "linewidth",
                "linestyle",
                "alpha",
                "marker"
            ],
            "zorder": 2,
            "visible": true
        },
        "ax_00_line_01": {
            "id": "ax_00_line_01",
            "axes_id": "ax_00",
            "element_type": "line",
            "label": "input envelope (Gaussian)",
            "geometry_px": {
                "coord_space": "axes",
                "bbox": {
                    "x0": 106,
                    "y0": 25,
                    "x1": 2219,
                    "y1": 238
                },
                "path_simplified": [
                    [
                        105.7,
                        238.3
                    ],
                    [
                        180.1,
                        227.9
                    ],
                    [
                        242.2,
                        217.6
                    ],
                    [
                        312.5,
                        204.1
                    ],
                    [
                        382.8,
                        188.7
                    ],
                    [
                        444.9,
                        173.7
                    ],
                    [
                        523.4,
                        153.1
                    ],
                    [
                        722.0,
                        97.5
                    ],
                    [
                        788.2,
                        79.8
                    ],
                    [
                        854.3,
                        63.6
                    ],
                    [
                        908.1,
                        52.0
                    ],
                    [
                        974.3,
                        40.1
                    ],
                    [
                        1036.3,
                        31.8
                    ],
                    [
                        1090.1,
                        27.1
                    ],
                    [
                        1152.2,
                        24.7
                    ],
                    [
                        1205.9,
                        25.4
                    ],
                    [
                        1239.0,
                        27.1
                    ],
                    [
                        1284.5,
                        30.9
                    ],
                    [
                        1354.8,
                        40.1
                    ],
                    [
                        1421.0,
                        52.0
                    ],
                    [
                        1474.8,
                        63.6
                    ],
                    [
                        1541.0,
                        79.8
                    ],
                    [
                        1607.1,
                        97.5
                    ],
                    [
                        1805.7,
                        153.1
                    ],
                    [
                        1867.7,
                        169.5
                    ],
                    [
                        1946.3,
                        188.7
                    ],
                    [
                        2016.6,
                        204.1
                    ],
                    [
                        2087.0,
                        217.6
                    ],
                    [
                        2149.0,
                        227.9
                    ],
                    [
                        2219.3,
                        237.8
                    ]
                ],
                "path": null
            },
            "style": {
                "color": [
                    0.5019607843137255,
                    0.5019607843137255,
                    0.5019607843137255
                ],
                "linewidth": 0.3401574803149607,
                "linestyle": ":",
                "alpha": null,
                "marker": "None",
                "markersize": 2.267716535433071
            },
            "editable_styles": [
                "color",
                "linewidth",
                "linestyle",
                "alpha",
                "marker"
            ],
            "zorder": 2,
            "visible": true
        },
        "ax_00_text_00": {
            "id": "ax_00_text_00",
            "axes_id": "ax_00",
            "element_type": "text",
            "label": "A",
            "text": "A",
            "geometry_px": {
                "coord_space": "axes",
                "bbox": {
                    "x0": -257,
                    "y0": -58,
                    "x1": -232,
                    "y1": -27
                },
                "anchor": {
                    "x": -106.1,
                    "y": 12.3
                }
            },
            "style": {
                "fontsize": 8.0,
                "color": "black",
                "fontweight": "bold",
                "fontstyle": "normal",
                "fontfamily": [
                    "Arial",
                    "Helvetica",
                    "DejaVu Sans",
                    "Liberation Sans"
                ],
                "alpha": null,
                "ha": "right",
                "va": "bottom",
                "rotation": 0.0
            },
            "editable_styles": [
                "fontsize",
                "color",
                "fontweight",
                "alpha"
            ],
            "zorder": 3,
            "visible": true
        },
        "ax_01_line_00": {
            "id": "ax_01_line_00",
            "axes_id": "ax_01",
            "element_type": "line",
            "label": "scipy.signal.hilbert",
            "geometry_px": {
                "coord_space": "axes",
                "bbox": {
                    "x0": 106,
                    "y0": 25,
                    "x1": 2219,
                    "y1": 518
                },
                "path_simplified": [
                    [
                        105.7,
                        510.1
                    ],
                    [
                        109.8,
                        515.3
                    ],
                    [
                        114.0,
                        517.5
                    ],
                    [
                        118.1,
                        518.3
                    ],
                    [
                        126.4,
                        517.8
                    ],
                    [
                        138.8,
                        514.3
                    ],
                    [
                        159.5,
                        505.8
                    ],
                    [
                        225.6,
                        475.1
                    ],
                    [
                        308.4,
                        441.0
                    ],
                    [
                        345.6,
                        423.0
                    ],
                    [
                        444.9,
                        368.4
                    ],
                    [
                        486.2,
                        344.2
                    ],
                    [
                        593.8,
                        276.1
                    ],
                    [
                        693.0,
                        211.2
                    ],
                    [
                        784.0,
                        154.3
                    ],
                    [
                        850.2,
                        116.9
                    ],
                    [
                        899.8,
                        91.6
                    ],
                    [
                        945.3,
                        71.6
                    ],
                    [
                        978.4,
                        58.8
                    ],
                    [
                        1007.4,
                        49.3
                    ],
                    [
                        1040.5,
                        40.2
                    ],
                    [
                        1065.3,
                        34.6
                    ],
                    [
                        1094.3,
                        29.7
                    ],
                    [
                        1123.2,
                        26.5
                    ],
                    [
                        1160.4,
                        24.7
                    ],
                    [
                        1193.5,
                        25.6
                    ],
                    [
                        1226.6,
                        28.6
                    ],
                    [
                        1251.4,
                        32.3
                    ],
                    [
                        1280.4,
                        38.2
                    ],
                    [
                        1313.5,
                        46.8
                    ],
                    [
                        1346.6,
                        57.4
                    ],
                    [
                        1375.5,
                        68.2
                    ],
                    [
                        1412.7,
                        84.0
                    ],
                    [
                        1470.7,
                        112.4
                    ],
                    [
                        1541.0,
                        152.0
                    ],
                    [
                        1615.4,
                        198.0
                    ],
                    [
                        1760.2,
                        292.0
                    ],
                    [
                        1822.2,
                        331.2
                    ],
                    [
                        1900.8,
                        378.0
                    ],
                    [
                        1962.9,
                        411.9
                    ],
                    [
                        2016.6,
                        438.8
                    ],
                    [
                        2074.5,
                        465.1
                    ],
                    [
                        2103.5,
                        475.5
                    ],
                    [
                        2132.5,
                        488.8
                    ],
                    [
                        2153.1,
                        492.8
                    ],
                    [
                        2161.4,
                        495.5
                    ],
                    [
                        2169.7,
                        500.4
                    ],
                    [
                        2182.1,
                        509.5
                    ],
                    [
                        2186.2,
                        511.3
                    ],
                    [
                        2190.4,
                        511.7
                    ],
                    [
                        2194.5,
                        510.4
                    ],
                    [
                        2206.9,
                        501.3
                    ],
                    [
                        2211.0,
                        499.4
                    ],
                    [
                        2215.2,
                        499.2
                    ],
                    [
                        2219.3,
                        502.9
                    ]
                ],
                "path": null
            },
            "style": {
                "color": [
                    0.0,
                    0.5019607843137255,
                    0.7529411764705882
                ],
                "linewidth": 2.0,
                "linestyle": "-",
                "alpha": null,
                "marker": "None",
                "markersize": 2.267716535433071
            },
            "editable_styles": [
                "color",
                "linewidth",
                "linestyle",
                "alpha",
                "marker"
            ],
            "zorder": 2,
            "visible": true
        },
        "ax_01_line_01": {
            "id": "ax_01_line_01",
            "axes_id": "ax_01",
            "element_type": "line",
            "label": "scitex_nn.Hilbert",
            "geometry_px": {
                "coord_space": "axes",
                "bbox": {
                    "x0": 106,
                    "y0": 25,
                    "x1": 2219,
                    "y1": 518
                },
                "path_simplified": [
                    [
                        105.7,
                        510.1
                    ],
                    [
                        109.8,
                        515.3
                    ],
                    [
                        114.0,
                        517.5
                    ],
                    [
                        118.1,
                        518.3
                    ],
                    [
                        126.4,
                        517.8
                    ],
                    [
                        138.8,
                        514.3
                    ],
                    [
                        159.5,
                        505.8
                    ],
                    [
                        225.6,
                        475.1
                    ],
                    [
                        308.4,
                        441.0
                    ],
                    [
                        345.6,
                        423.0
                    ],
                    [
                        444.9,
                        368.4
                    ],
                    [
                        486.2,
                        344.2
                    ],
                    [
                        593.8,
                        276.1
                    ],
                    [
                        693.0,
                        211.2
                    ],
                    [
                        784.0,
                        154.3
                    ],
                    [
                        850.2,
                        116.9
                    ],
                    [
                        899.8,
                        91.6
                    ],
                    [
                        945.3,
                        71.6
                    ],
                    [
                        978.4,
                        58.8
                    ],
                    [
                        1007.4,
                        49.3
                    ],
                    [
                        1040.5,
                        40.2
                    ],
                    [
                        1065.3,
                        34.6
                    ],
                    [
                        1094.3,
                        29.7
                    ],
                    [
                        1123.2,
                        26.5
                    ],
                    [
                        1160.4,
                        24.7
                    ],
                    [
                        1193.5,
                        25.6
                    ],
                    [
                        1226.6,
                        28.6
                    ],
                    [
                        1251.4,
                        32.3
                    ],
                    [
                        1280.4,
                        38.2
                    ],
                    [
                        1313.5,
                        46.8
                    ],
                    [
                        1346.6,
                        57.4
                    ],
                    [
                        1375.5,
                        68.2
                    ],
                    [
                        1412.7,
                        84.0
                    ],
                    [
                        1470.7,
                        112.4
                    ],
                    [
                        1541.0,
                        152.0
                    ],
                    [
                        1615.4,
                        198.0
                    ],
                    [
                        1760.2,
                        292.0
                    ],
                    [
                        1822.2,
                        331.2
                    ],
                    [
                        1900.8,
                        378.0
                    ],
                    [
                        1962.9,
                        411.9
                    ],
                    [
                        2016.6,
                        438.8
                    ],
                    [
                        2074.5,
                        465.1
                    ],
                    [
                        2103.5,
                        475.5
                    ],
                    [
                        2132.5,
                        488.8
                    ],
                    [
                        2153.1,
                        492.8
                    ],
                    [
                        2161.4,
                        495.5
                    ],
                    [
                        2169.7,
                        500.4
                    ],
                    [
                        2182.1,
                        509.5
                    ],
                    [
                        2186.2,
                        511.3
                    ],
                    [
                        2190.4,
                        511.7
                    ],
                    [
                        2194.5,
                        510.4
                    ],
                    [
                        2206.9,
                        501.3
                    ],
                    [
                        2211.0,
                        499.4
                    ],
                    [
                        2215.2,
                        499.2
                    ],
                    [
                        2219.3,
                        502.9
                    ]
                ],
                "path": null
            },
            "style": {
                "color": [
                    1.0,
                    0.27450980392156865,
                    0.19607843137254902
                ],
                "linewidth": 2.0,
                "linestyle": "--",
                "alpha": null,
                "marker": "None",
                "markersize": 2.267716535433071
            },
            "editable_styles": [
                "color",
                "linewidth",
                "linestyle",
                "alpha",
                "marker"
            ],
            "zorder": 2,
            "visible": true
        },
        "ax_01_text_00": {
            "id": "ax_01_text_00",
            "axes_id": "ax_01",
            "element_type": "text",
            "label": "B",
            "text": "B",
            "geometry_px": {
                "coord_space": "axes",
                "bbox": {
                    "x0": -257,
                    "y0": -58,
                    "x1": -232,
                    "y1": -27
                },
                "anchor": {
                    "x": -106.1,
                    "y": -3.8
                }
            },
            "style": {
                "fontsize": 8.0,
                "color": "black",
                "fontweight": "bold",
                "fontstyle": "normal",
                "fontfamily": [
                    "Arial",
                    "Helvetica",
                    "DejaVu Sans",
                    "Liberation Sans"
                ],
                "alpha": null,
                "ha": "right",
                "va": "bottom",
                "rotation": 0.0
            },
            "editable_styles": [
                "fontsize",
                "color",
                "fontweight",
                "alpha"
            ],
            "zorder": 3,
            "visible": true
        },
        "ax_02_line_00": {
            "id": "ax_02_line_00",
            "axes_id": "ax_02",
            "element_type": "line",
            "label": "scipy phase",
            "geometry_px": {
                "coord_space": "axes",
                "bbox": {
                    "x0": 106,
                    "y0": 25,
                    "x1": 2219,
                    "y1": 519
                },
                "path_simplified": [
                    [
                        105.7,
                        304.8
                    ],
                    [
                        118.1,
                        258.8
                    ],
                    [
                        134.6,
                        208.6
                    ],
                    [
                        155.3,
                        151.8
                    ],
                    [
                        200.8,
                        32.3
                    ],
                    [
                        205.0,
                        516.7
                    ],
                    [
                        250.5,
                        393.7
                    ],
                    [
                        287.7,
                        287.0
                    ],
                    [
                        333.2,
                        149.2
                    ],
                    [
                        370.4,
                        31.5
                    ],
                    [
                        374.5,
                        513.5
                    ],
                    [
                        411.8,
                        391.2
                    ],
                    [
                        444.9,
                        278.6
                    ],
                    [
                        482.1,
                        147.3
                    ],
                    [
                        515.2,
                        26.7
                    ],
                    [
                        519.3,
                        506.7
                    ],
                    [
                        581.4,
                        270.4
                    ],
                    [
                        639.3,
                        38.0
                    ],
                    [
                        643.4,
                        516.3
                    ],
                    [
                        697.2,
                        290.0
                    ],
                    [
                        755.1,
                        35.5
                    ],
                    [
                        759.2,
                        512.2
                    ],
                    [
                        813.0,
                        265.3
                    ],
                    [
                        862.6,
                        28.7
                    ],
                    [
                        866.8,
                        504.0
                    ],
                    [
                        912.3,
                        279.4
                    ],
                    [
                        961.9,
                        26.6
                    ],
                    [
                        966.0,
                        500.5
                    ],
                    [
                        1003.3,
                        305.0
                    ],
                    [
                        1052.9,
                        37.2
                    ],
                    [
                        1057.0,
                        509.8
                    ],
                    [
                        1094.3,
                        303.2
                    ],
                    [
                        1139.8,
                        44.3
                    ],
                    [
                        1143.9,
                        515.7
                    ],
                    [
                        1226.6,
                        26.4
                    ],
                    [
                        1230.7,
                        496.6
                    ],
                    [
                        1305.2,
                        35.8
                    ],
                    [
                        1309.3,
                        504.9
                    ],
                    [
                        1383.8,
                        24.7
                    ],
                    [
                        1387.9,
                        492.8
                    ],
                    [
                        1454.1,
                        49.6
                    ],
                    [
                        1458.2,
                        516.7
                    ],
                    [
                        1528.6,
                        29.0
                    ],
                    [
                        1532.7,
                        495.1
                    ],
                    [
                        1594.7,
                        50.3
                    ],
                    [
                        1598.9,
                        515.5
                    ],
                    [
                        1665.1,
                        26.0
                    ],
                    [
                        1669.2,
                        490.3
                    ],
                    [
                        1727.1,
                        49.3
                    ],
                    [
                        1731.2,
                        512.7
                    ],
                    [
                        1793.3,
                        27.1
                    ],
                    [
                        1797.4,
                        489.5
                    ],
                    [
                        1851.2,
                        57.6
                    ],
                    [
                        1855.3,
                        519.3
                    ],
                    [
                        1913.2,
                        42.6
                    ],
                    [
                        1917.4,
                        503.4
                    ],
                    [
                        1971.1,
                        50.1
                    ],
                    [
                        1975.3,
                        510.1
                    ],
                    [
                        2029.0,
                        46.4
                    ],
                    [
                        2033.2,
                        505.6
                    ],
                    [
                        2087.0,
                        31.5
                    ],
                    [
                        2091.1,
                        489.9
                    ],
                    [
                        2140.7,
                        42.4
                    ],
                    [
                        2144.9,
                        500.0
                    ],
                    [
                        2178.0,
                        200.9
                    ],
                    [
                        2194.5,
                        39.3
                    ],
                    [
                        2198.6,
                        495.2
                    ],
                    [
                        2211.0,
                        388.7
                    ],
                    [
                        2219.3,
                        328.3
                    ]
                ],
                "path": null
            },
            "style": {
                "color": [
                    0.0,
                    0.5019607843137255,
                    0.7529411764705882
                ],
                "linewidth": 1.0,
                "linestyle": "-",
                "alpha": null,
                "marker": "None",
                "markersize": 2.267716535433071
            },
            "editable_styles": [
                "color",
                "linewidth",
                "linestyle",
                "alpha",
                "marker"
            ],
            "zorder": 2,
            "visible": true
        },
        "ax_02_line_01": {
            "id": "ax_02_line_01",
            "axes_id": "ax_02",
            "element_type": "line",
            "label": "scitex_nn phase",
            "geometry_px": {
                "coord_space": "axes",
                "bbox": {
                    "x0": 106,
                    "y0": 25,
                    "x1": 2219,
                    "y1": 519
                },
                "path_simplified": [
                    [
                        105.7,
                        304.8
                    ],
                    [
                        118.1,
                        258.8
                    ],
                    [
                        134.6,
                        208.6
                    ],
                    [
                        155.3,
                        151.8
                    ],
                    [
                        200.8,
                        32.3
                    ],
                    [
                        205.0,
                        516.7
                    ],
                    [
                        250.5,
                        393.7
                    ],
                    [
                        287.7,
                        287.0
                    ],
                    [
                        333.2,
                        149.2
                    ],
                    [
                        370.4,
                        31.5
                    ],
                    [
                        374.5,
                        513.5
                    ],
                    [
                        411.8,
                        391.2
                    ],
                    [
                        444.9,
                        278.6
                    ],
                    [
                        482.1,
                        147.3
                    ],
                    [
                        515.2,
                        26.7
                    ],
                    [
                        519.3,
                        506.7
                    ],
                    [
                        581.4,
                        270.4
                    ],
                    [
                        639.3,
                        38.0
                    ],
                    [
                        643.4,
                        516.3
                    ],
                    [
                        697.2,
                        290.0
                    ],
                    [
                        755.1,
                        35.5
                    ],
                    [
                        759.2,
                        512.2
                    ],
                    [
                        813.0,
                        265.3
                    ],
                    [
                        862.6,
                        28.7
                    ],
                    [
                        866.8,
                        504.0
                    ],
                    [
                        912.3,
                        279.4
                    ],
                    [
                        961.9,
                        26.6
                    ],
                    [
                        966.0,
                        500.5
                    ],
                    [
                        1003.3,
                        305.0
                    ],
                    [
                        1052.9,
                        37.2
                    ],
                    [
                        1057.0,
                        509.8
                    ],
                    [
                        1094.3,
                        303.2
                    ],
                    [
                        1139.8,
                        44.3
                    ],
                    [
                        1143.9,
                        515.7
                    ],
                    [
                        1226.6,
                        26.4
                    ],
                    [
                        1230.7,
                        496.6
                    ],
                    [
                        1305.2,
                        35.8
                    ],
                    [
                        1309.3,
                        504.9
                    ],
                    [
                        1383.8,
                        24.7
                    ],
                    [
                        1387.9,
                        492.8
                    ],
                    [
                        1454.1,
                        49.6
                    ],
                    [
                        1458.2,
                        516.7
                    ],
                    [
                        1528.6,
                        29.0
                    ],
                    [
                        1532.7,
                        495.1
                    ],
                    [
                        1594.7,
                        50.3
                    ],
                    [
                        1598.9,
                        515.5
                    ],
                    [
                        1665.1,
                        26.0
                    ],
                    [
                        1669.2,
                        490.3
                    ],
                    [
                        1727.1,
                        49.3
                    ],
                    [
                        1731.2,
                        512.7
                    ],
                    [
                        1793.3,
                        27.1
                    ],
                    [
                        1797.4,
                        489.5
                    ],
                    [
                        1851.2,
                        57.6
                    ],
                    [
                        1855.3,
                        519.3
                    ],
                    [
                        1913.2,
                        42.6
                    ],
                    [
                        1917.4,
                        503.4
                    ],
                    [
                        1971.1,
                        50.1
                    ],
                    [
                        1975.3,
                        510.1
                    ],
                    [
                        2029.0,
                        46.4
                    ],
                    [
                        2033.2,
                        505.6
                    ],
                    [
                        2087.0,
                        31.5
                    ],
                    [
                        2091.1,
                        489.9
                    ],
                    [
                        2140.7,
                        42.4
                    ],
                    [
                        2144.9,
                        500.0
                    ],
                    [
                        2178.0,
                        200.9
                    ],
                    [
                        2194.5,
                        39.3
                    ],
                    [
                        2198.6,
                        495.2
                    ],
                    [
                        2211.0,
                        388.7
                    ],
                    [
                        2219.3,
                        328.3
                    ]
                ],
                "path": null
            },
            "style": {
                "color": [
                    1.0,
                    0.27450980392156865,
                    0.19607843137254902
                ],
                "linewidth": 1.0,
                "linestyle": "--",
                "alpha": null,
                "marker": "None",
                "markersize": 2.267716535433071
            },
            "editable_styles": [
                "color",
                "linewidth",
                "linestyle",
                "alpha",
                "marker"
            ],
            "zorder": 2,
            "visible": true
        },
        "ax_02_text_00": {
            "id": "ax_02_text_00",
            "axes_id": "ax_02",
            "element_type": "text",
            "label": "C",
            "text": "C",
            "geometry_px": {
                "coord_space": "axes",
                "bbox": {
                    "x0": -257,
                    "y0": -58,
                    "x1": -232,
                    "y1": -27
                },
                "anchor": {
                    "x": -106.1,
                    "y": 188.9
                }
            },
            "style": {
                "fontsize": 8.0,
                "color": "black",
                "fontweight": "bold",
                "fontstyle": "normal",
                "fontfamily": [
                    "Arial",
                    "Helvetica",
                    "DejaVu Sans",
                    "Liberation Sans"
                ],
                "alpha": null,
                "ha": "right",
                "va": "bottom",
                "rotation": 0.0
            },
            "editable_styles": [
                "fontsize",
                "color",
                "fontweight",
                "alpha"
            ],
            "zorder": 3,
            "visible": true
        }
    },
    "statistics": {},
    "data": {
        "csv_path": "hilbert_vs_scipy.csv",
        "columns_actual": [
            "ax_0_0_plot_000_x",
            "ax_0_0_plot_000_y",
            "ax_0_0_plot_001_x",
            "ax_0_0_plot_001_y",
            "ax_1_0_plot_002_x",
            "ax_1_0_plot_002_y",
            "ax_1_0_plot_003_x",
            "ax_1_0_plot_003_y",
            "ax_2_0_plot_004_x",
            "ax_2_0_plot_004_y",
            "ax_2_0_plot_005_x",
            "ax_2_0_plot_005_y"
        ],
        "csv_hash": "e68d16a79c84644c"
    },
    "output": {
        "format": "png",
        "width_px": 3000,
        "height_px": 2400
    }
}